<?xml version="1.0" encoding="utf-8" ?>
<AppSetting>
	<Refresh_Time>
		<Get_Data>60</Get_Data>
	</Refresh_Time>
	<Local>
		<RunText_XML>\Resources\Data\chtvInfoData\Buffer\chtvInfoData.xml</RunText_XML>
		<CheckPlayList_XML>\Resources\Data\PlayList\PlayList.xml</CheckPlayList_XML>
		<PlayList_XML>\Resources\Setting\PlayList.xml</PlayList_XML>
		<Movie_path>\Resources\movies\</Movie_path>
		<PlayLog>\Resources\Export_Data\Player\</PlayLog>
	</Local>
	<Net>
		<CreateNet_Bat>\Resources\Setting\CreateNetDir.bat</CreateNet_Bat>
		<DownLoad_Path>\\127.0.0.1\d\DownLoad\</DownLoad_Path>
		<UpLoad_Path>\\127.0.0.1\d\UpLoad\</UpLoad_Path>
	</Net>
</AppSetting>